Python_Studio/__init__.py
Python_Studio/setup.py
python_studio-0.4.dist-info/METADATA
python_studio-0.4.dist-info/WHEEL
python_studio-0.4.dist-info/top_level.txt
python_studio-0.4.dist-info/RECORD
