Metadata-Version: 2.1
Name: python-studio
Version: 0.4
Summary: studio for running apps
Home-page: UNKNOWN
Author: Tony Stark
Author-email: xsumagravity@gmail.com
License: UNKNOWN
Platform: UNKNOWN
Classifier: Programming Language :: Python :: 3
Classifier: License :: OSI Approved :: MIT License
Classifier: Operating System :: OS Independent
Requires-Python: >=3.6
